cachesql/__init__.py
cachesql/serializer.py
cachesql/sql.py
cachesql/store.py
cachesql/utils.py
cachesql-0.3.0.dist-info/LICENSE
cachesql-0.3.0.dist-info/METADATA
cachesql-0.3.0.dist-info/WHEEL
cachesql-0.3.0.dist-info/RECORD
