Metadata-Version: 2.1
Name: cachesql
Version: 0.3.0
Summary: Fast, resilient and reproducible data analysis with cached SQL queries
Home-page: https://github.com/felipeam86/cachesql
License: MIT
Author: Felipe Aguirre Martinez
Author-email: felipeam86@gmail.com
Requires-Python: >=3.8,<4.0
Classifier: License :: OSI Approved :: MIT License
Classifier: Programming Language :: Python :: 3
Classifier: Programming Language :: Python :: 3.8
Classifier: Programming Language :: Python :: 3.9
Classifier: Programming Language :: Python :: 3.10
Classifier: Programming Language :: Python :: 3.11
Requires-Dist: SQLAlchemy (>=1.4.0,<3.0.0)
Requires-Dist: joblib (>=1.0.0,<2.0.0)
Requires-Dist: pandas (>=1.5.3,<3.0.0)
Requires-Dist: pyarrow (>=10.0.0)
Requires-Dist: sqlparse (>=0.4.4,<0.5.0)
